{
  "project_info": {
    "project_number": "105221129621",
    "project_id": "belstomnew",
    "storage_bucket": "belstomnew.appspot.com"
  },
  "client": [
    {
      "client_info": {
        "mobilesdk_app_id": "1:105221129621:android:3f215bc5742af0295d229c",
        "android_client_info": {
          "package_name": "com.example.belstom"
        }
      },
      "oauth_client": [
        {
          "client_id": "105221129621-990g713md1a8h3rbgdksctpfqoubt02j.apps.googleusercontent.com",
          "client_type": 3
        }
      ],
      "api_key": [
        {
          "current_key": "AIzaSyALdiaaJMKJ4uWS7-4AG0-tFQyI3ElgaeA"
        }
      ],
      "services": {
        "appinvite_service": {
          "other_platform_oauth_client": [
            {
              "client_id": "105221129621-990g713md1a8h3rbgdksctpfqoubt02j.apps.googleusercontent.com",
              "client_type": 3
            }
          ]
        }
      }
    }
  ],
  "configuration_version": "1"
}